napolipy/__init__.py
napolipy/__main__.py
napolipy-1.0.2.dist-info/METADATA
napolipy-1.0.2.dist-info/WHEEL
napolipy-1.0.2.dist-info/licenses/LICENSE
napolipy-1.0.2.dist-info/RECORD
