Metadata-Version: 2.1
Name: napolipy
Version: 1.0.2
Summary: Napoli Unicode Logo generator (not affiliated with Società Sportiva Calcio Napoli)
Project-URL: Homepage, https://github.com/TheDarkBug/napolipy
Project-URL: Bug Tracker, https://github.com/TheDarkBug/napolipy/issues
Author-email: Adriano Oliviero <adrianoliviero23@gmail.com>
License-File: LICENSE
Classifier: License :: OSI Approved :: MIT License
Classifier: Operating System :: OS Independent
Classifier: Programming Language :: Python :: 3
Requires-Python: >=3.7
